{"decls":[{"kind":"export","names":["scan.model.artifact_v1","scan.model.bundle_v1","scan.model.dimension_v1","scan.model.dm_bool_v1","scan.model.dm_null_v1","scan.model.dm_number_i32_v1","scan.model.dm_string_v1","scan.model.finding_v1"]},{"body":["begin",["let","pl",["std.vec.with_capacity",256]],["let","k",0],["set","pl",["scan.dm.payload_push_entry_v1","pl",["bytes.view_lit","id"],["scan.model.dm_string_v1","id"]]],["set","k",["+","k",1]],["set","pl",["scan.dm.payload_push_entry_v1","pl",["bytes.view_lit","kind"],["scan.model.dm_string_v1","kind"]]],["set","k",["+","k",1]],["set","pl",["scan.dm.payload_push_entry_v1","pl",["bytes.view_lit","path"],["scan.model.dm_string_v1","path"]]],["set","k",["+","k",1]],["set","pl",["scan.dm.payload_push_entry_v1","pl",["bytes.view_lit","digest"],["scan.model.dm_string_v1","digest_hex"]]],["set","k",["+","k",1]],["set","pl",["scan.dm.payload_push_entry_v1","pl",["bytes.view_lit","content_type"],["scan.model.dm_string_v1","content_type"]]],["set","k",["+","k",1]],["let","pl_b",["std.vec.as_bytes","pl"]],["scan.dm.map_from_entries_v1","k",["bytes.view","pl_b"]]],"kind":"defn","name":"scan.model.artifact_v1","params":[{"name":"id","ty":"bytes_view"},{"name":"kind","ty":"bytes_view"},{"name":"path","ty":"bytes_view"},{"name":"digest_hex","ty":"bytes_view"},{"name":"content_type","ty":"bytes_view"}],"result":"bytes"},{"body":["begin",["let","pl",["std.vec.with_capacity",512]],["let","k",0],["set","pl",["scan.dm.payload_push_entry_v1","pl",["bytes.view_lit","dimension"],"dimension"]],["set","k",["+","k",1]],["set","pl",["scan.dm.payload_push_entry_v1","pl",["bytes.view_lit","findings"],"findings"]],["set","k",["+","k",1]],["set","pl",["scan.dm.payload_push_entry_v1","pl",["bytes.view_lit","artifacts"],"artifacts"]],["set","k",["+","k",1]],["let","pl_b",["std.vec.as_bytes","pl"]],["scan.dm.map_from_entries_v1","k",["bytes.view","pl_b"]]],"kind":"defn","name":"scan.model.bundle_v1","params":[{"name":"dimension","ty":"bytes"},{"name":"findings","ty":"bytes"},{"name":"artifacts","ty":"bytes"}],"result":"bytes"},{"body":["begin",["let","pl",["std.vec.with_capacity",512]],["let","k",0],["set","pl",["scan.dm.payload_push_entry_v1","pl",["bytes.view_lit","name"],["scan.model.dm_string_v1","name"]]],["set","k",["+","k",1]],["set","pl",["scan.dm.payload_push_entry_v1","pl",["bytes.view_lit","status"],["scan.model.dm_string_v1","status"]]],["set","k",["+","k",1]],["set","pl",["scan.dm.payload_push_entry_v1","pl",["bytes.view_lit","score"],"score"]],["set","k",["+","k",1]],["set","pl",["scan.dm.payload_push_entry_v1","pl",["bytes.view_lit","weight"],["ext.data_model.value_number","weight_num"]]],["set","k",["+","k",1]],["set","pl",["scan.dm.payload_push_entry_v1","pl",["bytes.view_lit","metrics"],"metrics"]],["set","k",["+","k",1]],["set","pl",["scan.dm.payload_push_entry_v1","pl",["bytes.view_lit","finding_refs"],"finding_refs"]],["set","k",["+","k",1]],["set","pl",["scan.dm.payload_push_entry_v1","pl",["bytes.view_lit","artifact_refs"],"artifact_refs"]],["set","k",["+","k",1]],["let","pl_b",["std.vec.as_bytes","pl"]],["scan.dm.map_from_entries_v1","k",["bytes.view","pl_b"]]],"kind":"defn","name":"scan.model.dimension_v1","params":[{"name":"name","ty":"bytes_view"},{"name":"status","ty":"bytes_view"},{"name":"score","ty":"bytes"},{"name":"weight_num","ty":"bytes_view"},{"name":"metrics","ty":"bytes"},{"name":"finding_refs","ty":"bytes"},{"name":"artifact_refs","ty":"bytes"}],"result":"bytes"},{"body":["ext.data_model.value_bool","b"],"kind":"defn","name":"scan.model.dm_bool_v1","params":[{"name":"b","ty":"i32"}],"result":"bytes"},{"body":["ext.data_model.value_null"],"kind":"defn","name":"scan.model.dm_null_v1","params":[],"result":"bytes"},{"body":["begin",["let","s",["std.fmt.s32_to_dec","n"]],["ext.data_model.value_number",["bytes.view","s"]]],"kind":"defn","name":"scan.model.dm_number_i32_v1","params":[{"name":"n","ty":"i32"}],"result":"bytes"},{"body":["ext.data_model.value_string","s"],"kind":"defn","name":"scan.model.dm_string_v1","params":[{"name":"s","ty":"bytes_view"}],"result":"bytes"},{"body":["begin",["let","pl",["std.vec.with_capacity",512]],["let","k",0],["set","pl",["scan.dm.payload_push_entry_v1","pl",["bytes.view_lit","code"],["scan.model.dm_string_v1","code"]]],["set","k",["+","k",1]],["set","pl",["scan.dm.payload_push_entry_v1","pl",["bytes.view_lit","dimension"],["scan.model.dm_string_v1","dimension"]]],["set","k",["+","k",1]],["set","pl",["scan.dm.payload_push_entry_v1","pl",["bytes.view_lit","severity"],["scan.model.dm_string_v1","severity"]]],["set","k",["+","k",1]],["set","pl",["scan.dm.payload_push_entry_v1","pl",["bytes.view_lit","title"],["scan.model.dm_string_v1","title"]]],["set","k",["+","k",1]],["set","pl",["scan.dm.payload_push_entry_v1","pl",["bytes.view_lit","summary"],["scan.model.dm_string_v1","summary"]]],["set","k",["+","k",1]],["set","pl",["scan.dm.payload_push_entry_v1","pl",["bytes.view_lit","evidence"],"evidence"]],["set","k",["+","k",1]],["set","pl",["scan.dm.payload_push_entry_v1","pl",["bytes.view_lit","suggested_fix"],["scan.model.dm_string_v1","suggested_fix"]]],["set","k",["+","k",1]],["set","pl",["scan.dm.payload_push_entry_v1","pl",["bytes.view_lit","docs_ref"],["scan.model.dm_string_v1","docs_ref"]]],["set","k",["+","k",1]],["let","pl_b",["std.vec.as_bytes","pl"]],["scan.dm.map_from_entries_v1","k",["bytes.view","pl_b"]]],"kind":"defn","name":"scan.model.finding_v1","params":[{"name":"dimension","ty":"bytes_view"},{"name":"code","ty":"bytes_view"},{"name":"severity","ty":"bytes_view"},{"name":"title","ty":"bytes_view"},{"name":"summary","ty":"bytes_view"},{"name":"evidence","ty":"bytes"},{"name":"suggested_fix","ty":"bytes_view"},{"name":"docs_ref","ty":"bytes_view"}],"result":"bytes"}],"imports":["ext.data_model","scan.dm","std.fmt","std.vec"],"kind":"module","module_id":"scan.model","schema_version":"x07.x07ast@0.8.0"}
